fastapi_yaml/__init__.py
fastapi_yaml/main.py
fastapi_yaml-0.2.0.dist-info/METADATA
fastapi_yaml-0.2.0.dist-info/WHEEL
fastapi_yaml-0.2.0.dist-info/RECORD
