Metadata-Version: 2.1
Name: fastapi-yaml
Version: 0.2.0
Summary: Handle YAML data in FastAPI
Home-page: https://github.com/chermed/fastapi-yaml
License: MIT
Author: Mohamed Cherkaoui
Author-email: chermed@gmail.com
Requires-Python: >=3.11
Classifier: License :: OSI Approved :: MIT License
Classifier: Programming Language :: Python :: 3
Classifier: Programming Language :: Python :: 3.11
Requires-Dist: fastapi (>=0.100.0)
Requires-Dist: python-multipart (>=0.0.6,<0.1.0)
Requires-Dist: pyyaml (>=6.0)
